{
 "custom_fields": [
  {
   "_assign": null,
   "_comments": null,
   "_liked_by": null,
   "_user_tags": null,
   "allow_in_quick_entry": 0,
   "allow_on_submit": 0,
   "bold": 0,
   "collapsible": 0,
   "collapsible_depends_on": null,
   "columns": 0,
   "creation": "2025-12-18 15:57:18.508665",
   "default": "0",
   "depends_on": null,
   "description": null,
   "docstatus": 0,
   "dt": "Purchase Invoice",
   "fetch_from": null,
   "fetch_if_empty": 0,
   "fieldname": "biaya_lainnya",
   "fieldtype": "Currency",
   "hidden": 0,
   "hide_border": 0,
   "hide_days": 0,
   "hide_seconds": 0,
   "idx": 92,
   "ignore_user_permissions": 0,
   "ignore_xss_filter": 0,
   "in_global_search": 0,
   "in_list_view": 0,
   "in_preview": 0,
   "in_standard_filter": 0,
   "insert_after": "pph",
   "is_system_generated": 0,
   "is_virtual": 0,
   "label": "Biaya Lainnya",
   "length": 0,
   "link_filters": null,
   "mandatory_depends_on": null,
   "modified": "2025-12-18 15:57:18.508665",
   "modified_by": "Administrator",
   "module": "Buying STH",
   "name": "Purchase Invoice-biaya_lainnya",
   "no_copy": 0,
   "non_negative": 0,
   "options": null,
   "owner": "Administrator",
   "permlevel": 0,
   "placeholder": null,
   "precision": "",
   "print_hide": 0,
   "print_hide_if_no_value": 0,
   "print_width": null,
   "read_only": 1,
   "read_only_depends_on": null,
   "report_hide": 0,
   "reqd": 0,
   "search_index": 0,
   "show_dashboard": 0,
   "sort_options": 0,
   "translatable": 0,
   "unique": 0,
   "width": null
  },
  {
   "_assign": null,
   "_comments": null,
   "_liked_by": null,
   "_user_tags": null,
   "allow_in_quick_entry": 0,
   "allow_on_submit": 0,
   "bold": 0,
   "collapsible": 0,
   "collapsible_depends_on": null,
   "columns": 0,
   "creation": "2025-12-18 15:57:16.690800",
   "default": null,
   "depends_on": null,
   "description": null,
   "docstatus": 0,
   "dt": "Purchase Invoice",
   "fetch_from": null,
   "fetch_if_empty": 0,
   "fieldname": "column_break_knktt",
   "fieldtype": "Column Break",
   "hidden": 0,
   "hide_border": 0,
   "hide_days": 0,
   "hide_seconds": 0,
   "idx": 87,
   "ignore_user_permissions": 0,
   "ignore_xss_filter": 0,
   "in_global_search": 0,
   "in_list_view": 0,
   "in_preview": 0,
   "in_standard_filter": 0,
   "insert_after": "section_break_g5g2k",
   "is_system_generated": 0,
   "is_virtual": 0,
   "label": "",
   "length": 0,
   "link_filters": null,
   "mandatory_depends_on": null,
   "modified": "2025-12-18 15:57:16.690800",
   "modified_by": "Administrator",
   "module": "Buying STH",
   "name": "Purchase Invoice-column_break_knktt",
   "no_copy": 0,
   "non_negative": 0,
   "options": null,
   "owner": "Administrator",
   "permlevel": 0,
   "placeholder": null,
   "precision": "",
   "print_hide": 0,
   "print_hide_if_no_value": 0,
   "print_width": null,
   "read_only": 0,
   "read_only_depends_on": null,
   "report_hide": 0,
   "reqd": 0,
   "search_index": 0,
   "show_dashboard": 0,
   "sort_options": 0,
   "translatable": 0,
   "unique": 0,
   "width": null
  },
  {
   "_assign": null,
   "_comments": null,
   "_liked_by": null,
   "_user_tags": null,
   "allow_in_quick_entry": 0,
   "allow_on_submit": 0,
   "bold": 0,
   "collapsible": 0,
   "collapsible_depends_on": null,
   "columns": 0,
   "creation": "2025-12-18 15:57:17.037876",
   "default": null,
   "depends_on": null,
   "description": null,
   "docstatus": 0,
   "dt": "Purchase Invoice",
   "fetch_from": null,
   "fetch_if_empty": 0,
   "fieldname": "column_break_z6c3x",
   "fieldtype": "Column Break",
   "hidden": 0,
   "hide_border": 0,
   "hide_days": 0,
   "hide_seconds": 0,
   "idx": 88,
   "ignore_user_permissions": 0,
   "ignore_xss_filter": 0,
   "in_global_search": 0,
   "in_list_view": 0,
   "in_preview": 0,
   "in_standard_filter": 0,
   "insert_after": "column_break_knktt",
   "is_system_generated": 0,
   "is_virtual": 0,
   "label": "",
   "length": 0,
   "link_filters": null,
   "mandatory_depends_on": null,
   "modified": "2025-12-18 15:57:17.037876",
   "modified_by": "Administrator",
   "module": "Buying STH",
   "name": "Purchase Invoice-column_break_z6c3x",
   "no_copy": 0,
   "non_negative": 0,
   "options": null,
   "owner": "Administrator",
   "permlevel": 0,
   "placeholder": null,
   "precision": "",
   "print_hide": 0,
   "print_hide_if_no_value": 0,
   "print_width": null,
   "read_only": 0,
   "read_only_depends_on": null,
   "report_hide": 0,
   "reqd": 0,
   "search_index": 0,
   "show_dashboard": 0,
   "sort_options": 0,
   "translatable": 0,
   "unique": 0,
   "width": null
  },
  {
   "_assign": null,
   "_comments": null,
   "_liked_by": null,
   "_user_tags": null,
   "allow_in_quick_entry": 0,
   "allow_on_submit": 0,
   "bold": 0,
   "collapsible": 0,
   "collapsible_depends_on": null,
   "columns": 0,
   "creation": "2026-01-07 14:34:15.391993",
   "default": null,
   "depends_on": "eval:doc.document_type",
   "description": null,
   "docstatus": 0,
   "dt": "Purchase Invoice",
   "fetch_from": "",
   "fetch_if_empty": 0,
   "fieldname": "document_no",
   "fieldtype": "Dynamic Link",
   "hidden": 0,
   "hide_border": 0,
   "hide_days": 0,
   "hide_seconds": 0,
   "idx": 10,
   "ignore_user_permissions": 0,
   "ignore_xss_filter": 0,
   "in_global_search": 0,
   "in_list_view": 0,
   "in_preview": 0,
   "in_standard_filter": 0,
   "insert_after": "document_type",
   "is_system_generated": 0,
   "is_virtual": 0,
   "label": "Document No",
   "length": 0,
   "link_filters": null,
   "mandatory_depends_on": null,
   "modified": "2026-01-07 14:34:15.391993",
   "modified_by": "Administrator",
   "module": "Buying STH",
   "name": "Purchase Invoice-document_no",
   "no_copy": 0,
   "non_negative": 0,
   "options": "document_type",
   "owner": "Administrator",
   "permlevel": 0,
   "placeholder": null,
   "precision": "",
   "print_hide": 1,
   "print_hide_if_no_value": 0,
   "print_width": null,
   "read_only": 0,
   "read_only_depends_on": null,
   "report_hide": 0,
   "reqd": 0,
   "search_index": 0,
   "show_dashboard": 0,
   "sort_options": 0,
   "translatable": 0,
   "unique": 0,
   "width": null
  },
  {
   "_assign": null,
   "_comments": null,
   "_liked_by": null,
   "_user_tags": null,
   "allow_in_quick_entry": 0,
   "allow_on_submit": 0,
   "bold": 0,
   "collapsible": 0,
   "collapsible_depends_on": null,
   "columns": 0,
   "creation": "2026-01-07 14:33:38.970268",
   "default": null,
   "depends_on": null,
   "description": null,
   "docstatus": 0,
   "dt": "Purchase Invoice",
   "fetch_from": "invoice_type.document_type",
   "fetch_if_empty": 0,
   "fieldname": "document_type",
   "fieldtype": "Link",
   "hidden": 1,
   "hide_border": 0,
   "hide_days": 0,
   "hide_seconds": 0,
   "idx": 9,
   "ignore_user_permissions": 0,
   "ignore_xss_filter": 0,
   "in_global_search": 0,
   "in_list_view": 0,
   "in_preview": 0,
   "in_standard_filter": 0,
   "insert_after": "invoice_type",
   "is_system_generated": 0,
   "is_virtual": 0,
   "label": "Document Type",
   "length": 0,
   "link_filters": null,
   "mandatory_depends_on": null,
   "modified": "2026-01-07 14:33:38.970268",
   "modified_by": "Administrator",
   "module": "Buying STH",
   "name": "Purchase Invoice-document_type",
   "no_copy": 0,
   "non_negative": 0,
   "options": "DocType",
   "owner": "Administrator",
   "permlevel": 0,
   "placeholder": null,
   "precision": "",
   "print_hide": 1,
   "print_hide_if_no_value": 0,
   "print_width": null,
   "read_only": 1,
   "read_only_depends_on": null,
   "report_hide": 0,
   "reqd": 0,
   "search_index": 0,
   "show_dashboard": 0,
   "sort_options": 0,
   "translatable": 0,
   "unique": 0,
   "width": null
  },
  {
   "_assign": null,
   "_comments": null,
   "_liked_by": null,
   "_user_tags": null,
   "allow_in_quick_entry": 0,
   "allow_on_submit": 0,
   "bold": 0,
   "collapsible": 0,
   "collapsible_depends_on": null,
   "columns": 0,
   "creation": "2025-12-18 15:57:17.359927",
   "default": "0",
   "depends_on": null,
   "description": null,
   "docstatus": 0,
   "dt": "Purchase Invoice",
   "fetch_from": null,
   "fetch_if_empty": 0,
   "fieldname": "dpp",
   "fieldtype": "Currency",
   "hidden": 0,
   "hide_border": 0,
   "hide_days": 0,
   "hide_seconds": 0,
   "idx": 89,
   "ignore_user_permissions": 0,
   "ignore_xss_filter": 0,
   "in_global_search": 0,
   "in_list_view": 0,
   "in_preview": 0,
   "in_standard_filter": 0,
   "insert_after": "column_break_z6c3x",
   "is_system_generated": 0,
   "is_virtual": 0,
   "label": "DPP",
   "length": 0,
   "link_filters": null,
   "mandatory_depends_on": null,
   "modified": "2025-12-18 15:57:17.359927",
   "modified_by": "Administrator",
   "module": "Buying STH",
   "name": "Purchase Invoice-dpp",
   "no_copy": 0,
   "non_negative": 0,
   "options": null,
   "owner": "Administrator",
   "permlevel": 0,
   "placeholder": null,
   "precision": "",
   "print_hide": 0,
   "print_hide_if_no_value": 0,
   "print_width": null,
   "read_only": 1,
   "read_only_depends_on": null,
   "report_hide": 0,
   "reqd": 0,
   "search_index": 0,
   "show_dashboard": 0,
   "sort_options": 0,
   "translatable": 0,
   "unique": 0,
   "width": null
  },
  {
   "_assign": null,
   "_comments": null,
   "_liked_by": null,
   "_user_tags": null,
   "allow_in_quick_entry": 0,
   "allow_on_submit": 0,
   "bold": 0,
   "collapsible": 0,
   "collapsible_depends_on": null,
   "columns": 0,
   "creation": "2026-01-07 14:26:20.721728",
   "default": null,
   "depends_on": null,
   "description": null,
   "docstatus": 0,
   "dt": "Purchase Invoice",
   "fetch_from": null,
   "fetch_if_empty": 0,
   "fieldname": "invoice_type",
   "fieldtype": "Link",
   "hidden": 0,
   "hide_border": 0,
   "hide_days": 0,
   "hide_seconds": 0,
   "idx": 8,
   "ignore_user_permissions": 0,
   "ignore_xss_filter": 0,
   "in_global_search": 0,
   "in_list_view": 0,
   "in_preview": 0,
   "in_standard_filter": 1,
   "insert_after": "voucher_type",
   "is_system_generated": 0,
   "is_virtual": 0,
   "label": "Invoice Type",
   "length": 0,
   "link_filters": null,
   "mandatory_depends_on": null,
   "modified": "2026-01-07 14:26:20.721728",
   "modified_by": "Administrator",
   "module": "Buying STH",
   "name": "Purchase Invoice-invoice_type",
   "no_copy": 0,
   "non_negative": 0,
   "options": "Purchase Invoice Type",
   "owner": "Administrator",
   "permlevel": 0,
   "placeholder": null,
   "precision": "",
   "print_hide": 1,
   "print_hide_if_no_value": 0,
   "print_width": null,
   "read_only": 0,
   "read_only_depends_on": null,
   "report_hide": 0,
   "reqd": 1,
   "search_index": 0,
   "show_dashboard": 0,
   "sort_options": 0,
   "translatable": 0,
   "unique": 0,
   "width": null
  },
  {
   "_assign": null,
   "_comments": null,
   "_liked_by": null,
   "_user_tags": null,
   "allow_in_quick_entry": 0,
   "allow_on_submit": 0,
   "bold": 0,
   "collapsible": 0,
   "collapsible_depends_on": null,
   "columns": 0,
   "creation": "2025-12-18 15:57:18.150879",
   "default": "0",
   "depends_on": null,
   "description": null,
   "docstatus": 0,
   "dt": "Purchase Invoice",
   "fetch_from": null,
   "fetch_if_empty": 0,
   "fieldname": "pph",
   "fieldtype": "Currency",
   "hidden": 0,
   "hide_border": 0,
   "hide_days": 0,
   "hide_seconds": 0,
   "idx": 91,
   "ignore_user_permissions": 0,
   "ignore_xss_filter": 0,
   "in_global_search": 0,
   "in_list_view": 0,
   "in_preview": 0,
   "in_standard_filter": 0,
   "insert_after": "ppn",
   "is_system_generated": 0,
   "is_virtual": 0,
   "label": "PPH",
   "length": 0,
   "link_filters": null,
   "mandatory_depends_on": null,
   "modified": "2025-12-18 15:57:18.150879",
   "modified_by": "Administrator",
   "module": "Buying STH",
   "name": "Purchase Invoice-pph",
   "no_copy": 0,
   "non_negative": 0,
   "options": null,
   "owner": "Administrator",
   "permlevel": 0,
   "placeholder": null,
   "precision": "",
   "print_hide": 0,
   "print_hide_if_no_value": 0,
   "print_width": null,
   "read_only": 1,
   "read_only_depends_on": null,
   "report_hide": 0,
   "reqd": 0,
   "search_index": 0,
   "show_dashboard": 0,
   "sort_options": 0,
   "translatable": 0,
   "unique": 0,
   "width": null
  },
  {
   "_assign": null,
   "_comments": null,
   "_liked_by": null,
   "_user_tags": null,
   "allow_in_quick_entry": 0,
   "allow_on_submit": 0,
   "bold": 0,
   "collapsible": 0,
   "collapsible_depends_on": null,
   "columns": 0,
   "creation": "2025-12-18 15:57:17.747627",
   "default": "0",
   "depends_on": null,
   "description": null,
   "docstatus": 0,
   "dt": "Purchase Invoice",
   "fetch_from": null,
   "fetch_if_empty": 0,
   "fieldname": "ppn",
   "fieldtype": "Currency",
   "hidden": 0,
   "hide_border": 0,
   "hide_days": 0,
   "hide_seconds": 0,
   "idx": 90,
   "ignore_user_permissions": 0,
   "ignore_xss_filter": 0,
   "in_global_search": 0,
   "in_list_view": 0,
   "in_preview": 0,
   "in_standard_filter": 0,
   "insert_after": "dpp",
   "is_system_generated": 0,
   "is_virtual": 0,
   "label": "PPN",
   "length": 0,
   "link_filters": null,
   "mandatory_depends_on": null,
   "modified": "2025-12-18 15:57:17.747627",
   "modified_by": "Administrator",
   "module": "Buying STH",
   "name": "Purchase Invoice-ppn",
   "no_copy": 0,
   "non_negative": 0,
   "options": null,
   "owner": "Administrator",
   "permlevel": 0,
   "placeholder": null,
   "precision": "",
   "print_hide": 0,
   "print_hide_if_no_value": 0,
   "print_width": null,
   "read_only": 1,
   "read_only_depends_on": null,
   "report_hide": 0,
   "reqd": 0,
   "search_index": 0,
   "show_dashboard": 0,
   "sort_options": 0,
   "translatable": 0,
   "unique": 0,
   "width": null
  },
  {
   "_assign": null,
   "_comments": null,
   "_liked_by": null,
   "_user_tags": null,
   "allow_in_quick_entry": 0,
   "allow_on_submit": 0,
   "bold": 0,
   "collapsible": 0,
   "collapsible_depends_on": null,
   "columns": 0,
   "creation": "2025-12-18 15:57:16.302833",
   "default": null,
   "depends_on": null,
   "description": null,
   "docstatus": 0,
   "dt": "Purchase Invoice",
   "fetch_from": null,
   "fetch_if_empty": 0,
   "fieldname": "section_break_g5g2k",
   "fieldtype": "Section Break",
   "hidden": 0,
   "hide_border": 0,
   "hide_days": 0,
   "hide_seconds": 0,
   "idx": 86,
   "ignore_user_permissions": 0,
   "ignore_xss_filter": 0,
   "in_global_search": 0,
   "in_list_view": 0,
   "in_preview": 0,
   "in_standard_filter": 0,
   "insert_after": "total_taxes_and_charges",
   "is_system_generated": 0,
   "is_virtual": 0,
   "label": "Totals",
   "length": 0,
   "link_filters": null,
   "mandatory_depends_on": null,
   "modified": "2025-12-18 15:57:16.302833",
   "modified_by": "Administrator",
   "module": "Buying STH",
   "name": "Purchase Invoice-section_break_g5g2k",
   "no_copy": 0,
   "non_negative": 0,
   "options": null,
   "owner": "Administrator",
   "permlevel": 0,
   "placeholder": null,
   "precision": "",
   "print_hide": 0,
   "print_hide_if_no_value": 0,
   "print_width": null,
   "read_only": 0,
   "read_only_depends_on": null,
   "report_hide": 0,
   "reqd": 0,
   "search_index": 0,
   "show_dashboard": 0,
   "sort_options": 0,
   "translatable": 0,
   "unique": 0,
   "width": null
  },
  {
   "_assign": null,
   "_comments": null,
   "_liked_by": null,
   "_user_tags": null,
   "allow_in_quick_entry": 0,
   "allow_on_submit": 0,
   "bold": 0,
   "collapsible": 0,
   "collapsible_depends_on": null,
   "columns": 0,
   "creation": "2025-12-02 15:32:08.193291",
   "default": null,
   "depends_on": null,
   "description": null,
   "docstatus": 0,
   "dt": "Purchase Invoice",
   "fetch_from": null,
   "fetch_if_empty": 0,
   "fieldname": "unit",
   "fieldtype": "Link",
   "hidden": 0,
   "hide_border": 0,
   "hide_days": 0,
   "hide_seconds": 0,
   "idx": 16,
   "ignore_user_permissions": 0,
   "ignore_xss_filter": 0,
   "in_global_search": 0,
   "in_list_view": 0,
   "in_preview": 0,
   "in_standard_filter": 1,
   "insert_after": "due_date",
   "is_system_generated": 0,
   "is_virtual": 0,
   "label": "Unit",
   "length": 0,
   "link_filters": null,
   "mandatory_depends_on": null,
   "modified": "2025-12-19 11:40:39.640235",
   "modified_by": "Administrator",
   "module": "Buying STH",
   "name": "Purchase Invoice-unit",
   "no_copy": 0,
   "non_negative": 0,
   "options": "Unit",
   "owner": "Administrator",
   "permlevel": 0,
   "placeholder": null,
   "precision": "",
   "print_hide": 0,
   "print_hide_if_no_value": 0,
   "print_width": null,
   "read_only": 0,
   "read_only_depends_on": null,
   "report_hide": 0,
   "reqd": 0,
   "search_index": 0,
   "show_dashboard": 0,
   "sort_options": 0,
   "translatable": 0,
   "unique": 0,
   "width": null
  },
  {
   "_assign": null,
   "_comments": null,
   "_liked_by": null,
   "_user_tags": null,
   "allow_in_quick_entry": 0,
   "allow_on_submit": 0,
   "bold": 0,
   "collapsible": 0,
   "collapsible_depends_on": null,
   "columns": 0,
   "creation": "2026-01-07 13:47:08.188692",
   "default": null,
   "depends_on": null,
   "description": null,
   "docstatus": 0,
   "dt": "Purchase Invoice",
   "fetch_from": null,
   "fetch_if_empty": 0,
   "fieldname": "voucher_type",
   "fieldtype": "Select",
   "hidden": 0,
   "hide_border": 0,
   "hide_days": 0,
   "hide_seconds": 0,
   "idx": 7,
   "ignore_user_permissions": 0,
   "ignore_xss_filter": 0,
   "in_global_search": 0,
   "in_list_view": 0,
   "in_preview": 0,
   "in_standard_filter": 1,
   "insert_after": "company",
   "is_system_generated": 0,
   "is_virtual": 0,
   "label": "Voucher Type",
   "length": 0,
   "link_filters": null,
   "mandatory_depends_on": null,
   "modified": "2026-01-07 13:47:08.188692",
   "modified_by": "Administrator",
   "module": "Buying STH",
   "name": "Purchase Invoice-voucher_type",
   "no_copy": 0,
   "non_negative": 0,
   "options": "Voucher Match\nNon Voucher Match",
   "owner": "Administrator",
   "permlevel": 0,
   "placeholder": null,
   "precision": "",
   "print_hide": 1,
   "print_hide_if_no_value": 0,
   "print_width": null,
   "read_only": 0,
   "read_only_depends_on": null,
   "report_hide": 0,
   "reqd": 1,
   "search_index": 0,
   "show_dashboard": 0,
   "sort_options": 0,
   "translatable": 0,
   "unique": 0,
   "width": null
  }
 ],
 "custom_perms": [],
 "doctype": "Purchase Invoice",
 "links": [],
 "property_setters": [
  {
   "_assign": null,
   "_comments": null,
   "_liked_by": null,
   "_user_tags": null,
   "creation": "2025-12-17 14:41:47.498098",
   "default_value": null,
   "doc_type": "Purchase Invoice",
   "docstatus": 0,
   "doctype_or_field": "DocField",
   "field_name": "buying_price_list",
   "idx": 0,
   "is_system_generated": 0,
   "modified": "2026-01-12 19:46:38.033120",
   "modified_by": "Administrator",
   "module": "Buying STH",
   "name": "Purchase Invoice-buying_price_list-hidden",
   "owner": "Administrator",
   "property": "hidden",
   "property_type": "Check",
   "row_name": null,
   "value": "1"
  },
  {
   "_assign": null,
   "_comments": null,
   "_liked_by": null,
   "_user_tags": null,
   "creation": "2025-12-17 14:41:47.626423",
   "default_value": null,
   "doc_type": "Purchase Invoice",
   "docstatus": 0,
   "doctype_or_field": "DocField",
   "field_name": "ignore_pricing_rule",
   "idx": 0,
   "is_system_generated": 0,
   "modified": "2026-01-12 19:46:38.084493",
   "modified_by": "Administrator",
   "module": "Buying STH",
   "name": "Purchase Invoice-ignore_pricing_rule-hidden",
   "owner": "Administrator",
   "property": "hidden",
   "property_type": "Check",
   "row_name": null,
   "value": "1"
  },
  {
   "_assign": null,
   "_comments": null,
   "_liked_by": null,
   "_user_tags": null,
   "creation": "2025-12-17 14:41:48.017391",
   "default_value": null,
   "doc_type": "Purchase Invoice",
   "docstatus": 0,
   "doctype_or_field": "DocField",
   "field_name": "is_subcontracted",
   "idx": 0,
   "is_system_generated": 0,
   "modified": "2026-01-12 19:46:38.128923",
   "modified_by": "Administrator",
   "module": "Buying STH",
   "name": "Purchase Invoice-is_subcontracted-hidden",
   "owner": "Administrator",
   "property": "hidden",
   "property_type": "Check",
   "row_name": null,
   "value": "1"
  },
  {
   "_assign": null,
   "_comments": null,
   "_liked_by": null,
   "_user_tags": null,
   "creation": "2025-12-17 14:39:54.047457",
   "default_value": null,
   "doc_type": "Purchase Invoice",
   "docstatus": 0,
   "doctype_or_field": "DocField",
   "field_name": "project",
   "idx": 0,
   "is_system_generated": 0,
   "modified": "2026-01-12 19:46:38.173741",
   "modified_by": "Administrator",
   "module": "Buying STH",
   "name": "Purchase Invoice-project-hidden",
   "owner": "Administrator",
   "property": "hidden",
   "property_type": "Check",
   "row_name": null,
   "value": "1"
  },
  {
   "_assign": null,
   "_comments": null,
   "_liked_by": null,
   "_user_tags": null,
   "creation": "2025-12-17 14:41:47.755479",
   "default_value": null,
   "doc_type": "Purchase Invoice",
   "docstatus": 0,
   "doctype_or_field": "DocField",
   "field_name": "scan_barcode",
   "idx": 0,
   "is_system_generated": 0,
   "modified": "2026-01-12 19:46:38.216878",
   "modified_by": "Administrator",
   "module": "Buying STH",
   "name": "Purchase Invoice-scan_barcode-hidden",
   "owner": "Administrator",
   "property": "hidden",
   "property_type": "Check",
   "row_name": null,
   "value": "1"
  },
  {
   "_assign": null,
   "_comments": null,
   "_liked_by": null,
   "_user_tags": null,
   "creation": "2025-12-18 15:57:16.129724",
   "default_value": null,
   "doc_type": "Purchase Invoice",
   "docstatus": 0,
   "doctype_or_field": "DocField",
   "field_name": "section_break_49",
   "idx": 0,
   "is_system_generated": 0,
   "modified": "2026-01-12 19:46:38.264689",
   "modified_by": "Administrator",
   "module": "Buying STH",
   "name": "Purchase Invoice-section_break_49-hidden",
   "owner": "Administrator",
   "property": "hidden",
   "property_type": "Check",
   "row_name": null,
   "value": "1"
  },
  {
   "_assign": null,
   "_comments": null,
   "_liked_by": null,
   "_user_tags": null,
   "creation": "2025-12-18 15:59:11.157796",
   "default_value": null,
   "doc_type": "Purchase Invoice",
   "docstatus": 0,
   "doctype_or_field": "DocField",
   "field_name": "totals",
   "idx": 0,
   "is_system_generated": 0,
   "modified": "2026-01-12 19:46:38.308809",
   "modified_by": "Administrator",
   "module": "Buying STH",
   "name": "Purchase Invoice-totals-hidden",
   "owner": "Administrator",
   "property": "hidden",
   "property_type": "Check",
   "row_name": null,
   "value": "1"
  },
  {
   "_assign": null,
   "_comments": null,
   "_liked_by": null,
   "_user_tags": null,
   "creation": "2025-12-17 14:41:47.885014",
   "default_value": null,
   "doc_type": "Purchase Invoice",
   "docstatus": 0,
   "doctype_or_field": "DocField",
   "field_name": "update_stock",
   "idx": 0,
   "is_system_generated": 0,
   "modified": "2026-01-12 19:46:38.351591",
   "modified_by": "Administrator",
   "module": "Buying STH",
   "name": "Purchase Invoice-update_stock-hidden",
   "owner": "Administrator",
   "property": "hidden",
   "property_type": "Check",
   "row_name": null,
   "value": "1"
  },
  {
   "_assign": null,
   "_comments": null,
   "_liked_by": null,
   "_user_tags": null,
   "creation": "2025-12-17 14:41:47.345095",
   "default_value": null,
   "doc_type": "Purchase Invoice",
   "docstatus": 0,
   "doctype_or_field": "DocField",
   "field_name": "use_transaction_date_exchange_rate",
   "idx": 0,
   "is_system_generated": 0,
   "modified": "2026-01-12 19:46:38.407278",
   "modified_by": "Administrator",
   "module": "Buying STH",
   "name": "Purchase Invoice-use_transaction_date_exchange_rate-hidden",
   "owner": "Administrator",
   "property": "hidden",
   "property_type": "Check",
   "row_name": null,
   "value": "1"
  }
 ],
 "sync_on_migrate": 1
}