{
 "custom_fields": [
  {
   "_assign": null,
   "_comments": null,
   "_liked_by": null,
   "_user_tags": null,
   "allow_in_quick_entry": 0,
   "allow_on_submit": 0,
   "bold": 0,
   "collapsible": 0,
   "collapsible_depends_on": null,
   "columns": 0,
   "creation": "2025-12-21 16:38:50.231988",
   "default": null,
   "depends_on": null,
   "description": null,
   "docstatus": 0,
   "dt": "Purchase Order",
   "fetch_from": null,
   "fetch_if_empty": 0,
   "fieldname": "keterangan",
   "fieldtype": "Small Text",
   "hidden": 0,
   "hide_border": 0,
   "hide_days": 0,
   "hide_seconds": 0,
   "idx": 17,
   "ignore_user_permissions": 0,
   "ignore_xss_filter": 0,
   "in_global_search": 0,
   "in_list_view": 0,
   "in_preview": 1,
   "in_standard_filter": 0,
   "insert_after": "waktu_penyerahan",
   "is_system_generated": 0,
   "is_virtual": 0,
   "label": "Keterangan",
   "length": 0,
   "link_filters": null,
   "mandatory_depends_on": null,
   "modified": "2025-12-21 16:38:50.231988",
   "modified_by": "Administrator",
   "module": "Procurement STH",
   "name": "Purchase Order-keterangan",
   "no_copy": 0,
   "non_negative": 0,
   "options": null,
   "owner": "Administrator",
   "permlevel": 0,
   "placeholder": null,
   "precision": "",
   "print_hide": 0,
   "print_hide_if_no_value": 0,
   "print_width": null,
   "read_only": 0,
   "read_only_depends_on": null,
   "report_hide": 0,
   "reqd": 0,
   "search_index": 0,
   "show_dashboard": 0,
   "sort_options": 0,
   "translatable": 1,
   "unique": 0,
   "width": null
  },
  {
   "_assign": null,
   "_comments": null,
   "_liked_by": null,
   "_user_tags": null,
   "allow_in_quick_entry": 0,
   "allow_on_submit": 1,
   "bold": 0,
   "collapsible": 0,
   "collapsible_depends_on": null,
   "columns": 0,
   "creation": "2025-12-21 16:38:49.670840",
   "default": null,
   "depends_on": null,
   "description": null,
   "docstatus": 0,
   "dt": "Purchase Order",
   "fetch_from": null,
   "fetch_if_empty": 0,
   "fieldname": "waktu_penyerahan",
   "fieldtype": "Date",
   "hidden": 0,
   "hide_border": 0,
   "hide_days": 0,
   "hide_seconds": 0,
   "idx": 16,
   "ignore_user_permissions": 0,
   "ignore_xss_filter": 0,
   "in_global_search": 0,
   "in_list_view": 0,
   "in_preview": 1,
   "in_standard_filter": 0,
   "insert_after": "unit",
   "is_system_generated": 0,
   "is_virtual": 0,
   "label": "Waktu Penyerahan",
   "length": 0,
   "link_filters": null,
   "mandatory_depends_on": null,
   "modified": "2025-12-21 16:38:49.670840",
   "modified_by": "Administrator",
   "module": "Procurement STH",
   "name": "Purchase Order-waktu_penyerahan",
   "no_copy": 0,
   "non_negative": 0,
   "options": null,
   "owner": "Administrator",
   "permlevel": 0,
   "placeholder": null,
   "precision": "",
   "print_hide": 0,
   "print_hide_if_no_value": 0,
   "print_width": null,
   "read_only": 0,
   "read_only_depends_on": null,
   "report_hide": 0,
   "reqd": 0,
   "search_index": 0,
   "show_dashboard": 0,
   "sort_options": 0,
   "translatable": 0,
   "unique": 0,
   "width": null
  }
 ],
 "custom_perms": [],
 "doctype": "Purchase Order",
 "links": [],
 "property_setters": [
  {
   "_assign": null,
   "_comments": null,
   "_liked_by": null,
   "_user_tags": null,
   "creation": "2025-12-23 17:38:13.216425",
   "default_value": null,
   "doc_type": "Purchase Order",
   "docstatus": 0,
   "doctype_or_field": "DocField",
   "field_name": "apply_tds",
   "idx": 0,
   "is_system_generated": 0,
   "modified": "2025-12-23 17:38:13.216425",
   "modified_by": "Administrator",
   "module": "Procurement STH",
   "name": "Purchase Order-apply_tds-hidden",
   "owner": "Administrator",
   "property": "hidden",
   "property_type": "Check",
   "row_name": null,
   "value": "1"
  },
  {
   "_assign": null,
   "_comments": null,
   "_liked_by": null,
   "_user_tags": null,
   "creation": "2025-12-23 17:45:59.230313",
   "default_value": null,
   "doc_type": "Purchase Order",
   "docstatus": 0,
   "doctype_or_field": "DocField",
   "field_name": "currency_and_price_list",
   "idx": 0,
   "is_system_generated": 0,
   "modified": "2025-12-23 17:45:59.230313",
   "modified_by": "Administrator",
   "module": "Procurement STH",
   "name": "Purchase Order-currency_and_price_list-hidden",
   "owner": "Administrator",
   "property": "hidden",
   "property_type": "Check",
   "row_name": null,
   "value": "1"
  },
  {
   "_assign": null,
   "_comments": null,
   "_liked_by": null,
   "_user_tags": null,
   "creation": "2025-12-23 17:38:13.492692",
   "default_value": null,
   "doc_type": "Purchase Order",
   "docstatus": 0,
   "doctype_or_field": "DocField",
   "field_name": "is_subcontracted",
   "idx": 0,
   "is_system_generated": 0,
   "modified": "2025-12-23 17:38:13.492692",
   "modified_by": "Administrator",
   "module": "Procurement STH",
   "name": "Purchase Order-is_subcontracted-hidden",
   "owner": "Administrator",
   "property": "hidden",
   "property_type": "Check",
   "row_name": null,
   "value": "1"
  },
  {
   "_assign": null,
   "_comments": null,
   "_liked_by": null,
   "_user_tags": null,
   "creation": "2025-12-21 16:35:14.698473",
   "default_value": null,
   "doc_type": "Purchase Order",
   "docstatus": 0,
   "doctype_or_field": "DocType",
   "field_name": null,
   "idx": 0,
   "is_system_generated": 0,
   "modified": "2025-12-23 17:26:26.907541",
   "modified_by": "Administrator",
   "module": "Procurement STH",
   "name": "Purchase Order-main-default_view",
   "owner": "Administrator",
   "property": "default_view",
   "property_type": "Select",
   "row_name": null,
   "value": "Report"
  },
  {
   "_assign": null,
   "_comments": null,
   "_liked_by": null,
   "_user_tags": null,
   "creation": "2025-12-23 17:50:56.085477",
   "default_value": null,
   "doc_type": "Purchase Order",
   "docstatus": 0,
   "doctype_or_field": "DocField",
   "field_name": "scan_barcode",
   "idx": 0,
   "is_system_generated": 0,
   "modified": "2025-12-23 17:50:56.085477",
   "modified_by": "Administrator",
   "module": "Procurement STH",
   "name": "Purchase Order-scan_barcode-hidden",
   "owner": "Administrator",
   "property": "hidden",
   "property_type": "Check",
   "row_name": null,
   "value": "1"
  }
 ],
 "sync_on_migrate": 1
}